data_factory/__init__.py
data_factory/exceptions.py
data_factory/exporter.py
data_factory/loader.py
data_factory/pipeline.py
data_factory/steps.py
data_factory/validations.py
scalde_data_factory-0.0.1.dist-info/METADATA
scalde_data_factory-0.0.1.dist-info/WHEEL
scalde_data_factory-0.0.1.dist-info/top_level.txt
scalde_data_factory-0.0.1.dist-info/RECORD
