Metadata-Version: 2.1
Name: scalde-data-factory
Version: 0.0.1
Summary: Data preparations tools for data science projects
Author-email: Thomas Marquis <thomas.marquis.dev@gmail.com>
Keywords: datascience,preprocessing,data-pipeline,data-validation
Classifier: Development Status :: 3 - Alpha
Classifier: Programming Language :: Python :: 3.10
Classifier: Programming Language :: Python :: 3.11
Requires-Python: >=3.10
Requires-Dist: pandas (>=1.0.0)
Requires-Dist: rich (>=13.3.4)
